unittest_additions.py
unittest_additions-0.1.3.dist-info/LICENSE
unittest_additions-0.1.3.dist-info/METADATA
unittest_additions-0.1.3.dist-info/WHEEL
unittest_additions-0.1.3.dist-info/top_level.txt
unittest_additions-0.1.3.dist-info/RECORD
