Metadata-Version: 2.1
Name: unittest_additions
Version: 0.1.3
Summary: Additional features to extend python unittest and mock.
Home-page: https://github.com/c0yote/unittest-additions
Author: U.G. Wilson
Author-email: ugwilson@gmail.com
License: UNKNOWN
Project-URL: Bug Reports, https://github.com/c0yote/unittest-additions/issues
Project-URL: Source, https://github.com/c0yote/unittest-additions
Keywords: unittest mock
Platform: UNKNOWN
Classifier: Development Status :: 5 - Production/Stable
Classifier: Intended Audience :: Developers
Classifier: License :: OSI Approved :: MIT License
Classifier: Topic :: Software Development :: Testing
Classifier: Topic :: Software Development :: Testing :: Mocking
Classifier: Topic :: Software Development :: Testing :: Unit
Classifier: Programming Language :: Python :: 3.7
